windmill_sdk/__init__.py
windmill_sdk/clients/__init__.py
windmill_sdk/clients/base_client.py
windmill_sdk/clients/directus.py
windmill_sdk/clients/factory.py
windmill_sdk/clients/pocketbase.py
windmill_sdk/clients/sdc.py
windmill_sdk/models.py
windmill_sdk/notifiers/slack.py
windmill_sdk-1.0.0.dist-info/LICENSE
windmill_sdk-1.0.0.dist-info/METADATA
windmill_sdk-1.0.0.dist-info/WHEEL
windmill_sdk-1.0.0.dist-info/RECORD
