Metadata-Version: 2.3
Name: windmill-sdk
Version: 1.0.0
Summary: Libreria Python asincrona per interagire con PocketBase e SDC, pensata per Windmill
License: MIT
Author: Emily Lancietti
Author-email: emily.lancietti@opencontent.it
Requires-Python: >=3.10,<4.0
Classifier: License :: OSI Approved :: MIT License
Classifier: Programming Language :: Python :: 3
Classifier: Programming Language :: Python :: 3.10
Classifier: Programming Language :: Python :: 3.11
Classifier: Programming Language :: Python :: 3.12
Classifier: Programming Language :: Python :: 3.13
Requires-Dist: httpx (>=0.27.0,<0.28.0)
Requires-Dist: pydantic (>=2.6,<3.0)
